{
    "_links": {
        "self": {
            "href": ""
        },
        "type": {
            "href": "http:\/\/drupal.org\/rest\/type\/paragraph\/sidebar_menu"
        },
        "http:\/\/drupal.org\/rest\/relation\/paragraph\/sidebar_menu\/uid": [
            {
                "href": "http:\/\/default\/user\/1?_format=hal_json",
                "lang": "en"
            }
        ],
        "http:\/\/drupal.org\/rest\/relation\/paragraph\/sidebar_menu\/revision_uid": [
            {
                "href": "http:\/\/default\/user\/1?_format=hal_json"
            }
        ]
    },
    "id": [
        {
            "value": 645
        }
    ],
    "uuid": [
        {
            "value": "1f7d7442-3518-4617-81dd-b6d40a2a5ed2"
        }
    ],
    "revision_id": [
        {
            "value": 693
        }
    ],
    "langcode": [
        {
            "value": "en",
            "lang": "en"
        }
    ],
    "type": [
        {
            "target_id": "sidebar_menu"
        }
    ],
    "_embedded": {
        "http:\/\/drupal.org\/rest\/relation\/paragraph\/sidebar_menu\/uid": [
            {
                "_links": {
                    "self": {
                        "href": "http:\/\/default\/user\/1?_format=hal_json"
                    },
                    "type": {
                        "href": "http:\/\/drupal.org\/rest\/type\/user\/user"
                    }
                },
                "uuid": [
                    {
                        "value": "54b5f191-c1d0-4eb1-aec4-426a280024d2"
                    }
                ],
                "lang": "en"
            }
        ],
        "http:\/\/drupal.org\/rest\/relation\/paragraph\/sidebar_menu\/revision_uid": [
            {
                "_links": {
                    "self": {
                        "href": "http:\/\/default\/user\/1?_format=hal_json"
                    },
                    "type": {
                        "href": "http:\/\/drupal.org\/rest\/type\/user\/user"
                    }
                },
                "uuid": [
                    {
                        "value": "54b5f191-c1d0-4eb1-aec4-426a280024d2"
                    }
                ]
            }
        ]
    },
    "status": [
        {
            "value": true,
            "lang": "en"
        }
    ],
    "created": [
        {
            "value": "2020-03-16T15:51:58+00:00",
            "lang": "en",
            "format": "Y-m-d\\TH:i:sP"
        }
    ],
    "parent_id": [
        {
            "value": "450"
        }
    ],
    "parent_type": [
        {
            "value": "node"
        }
    ],
    "parent_field_name": [
        {
            "value": "field_sidebar_content"
        }
    ],
    "behavior_settings": [
        {
            "value": []
        }
    ],
    "default_langcode": [
        {
            "value": true,
            "lang": "en"
        }
    ],
    "field_prgf_sidebar_menu_ref": [
        {
            "plugin_id": "system_menu_block:membership-sidebar",
            "plugin_configuration": {
                "id": "system_menu_block:membership-sidebar",
                "label": "Sidebar Menu",
                "provider": "system",
                "label_display": 0,
                "level": "1",
                "depth": "1",
                "expand_all_items": 0
            },
            "lang": "en"
        }
    ]
}